pergamon_theme_server/__init__.py
pergamon_theme_server/_version.py
pergamon_theme_server/handlers.py
pergamon_theme_server-0.1.1.data/data/etc/jupyter/jupyter_server_config.d/pergamon_theme_server.json
pergamon_theme_server-0.1.1.data/data/share/jupyter/labextensions/pergamon_theme_server/package.json
pergamon_theme_server-0.1.1.data/data/share/jupyter/labextensions/pergamon_theme_server/schemas/pergamon_theme_server/package.json.orig
pergamon_theme_server-0.1.1.data/data/share/jupyter/labextensions/pergamon_theme_server/schemas/pergamon_theme_server/plugin.json
pergamon_theme_server-0.1.1.data/data/share/jupyter/labextensions/pergamon_theme_server/static/675.eb154ef3ea21ffd7ff8c.js
pergamon_theme_server-0.1.1.data/data/share/jupyter/labextensions/pergamon_theme_server/static/728.e2d718464e526bd402aa.js
pergamon_theme_server-0.1.1.data/data/share/jupyter/labextensions/pergamon_theme_server/static/remoteEntry.c06e876edf02b1d53880.js
pergamon_theme_server-0.1.1.data/data/share/jupyter/labextensions/pergamon_theme_server/static/style.js
pergamon_theme_server-0.1.1.data/data/share/jupyter/labextensions/pergamon_theme_server/static/third-party-licenses.json
pergamon_theme_server-0.1.1.data/data/share/jupyter/labextensions/pergamon_theme_server/install.json
pergamon_theme_server-0.1.1.dist-info/METADATA
pergamon_theme_server-0.1.1.dist-info/WHEEL
pergamon_theme_server-0.1.1.dist-info/licenses/LICENSE
pergamon_theme_server-0.1.1.dist-info/RECORD
